{
  "seed": 42,
  "best_epoch": 2,
  "best_val_metric": 0.9535230891719745,
  "final_train_loss": 0.1874783770645709,
  "final_val_loss": 0.15704781279727154,
  "final_val_metric": 0.9535230891719745,
  "val_accuracy": 0.9535230891719745,
  "history": {
    "train_losses": [
      0.5696854161484467,
      0.1874783770645709
    ],
    "train_metrics": [
      0.8292439258312021,
      0.9443134590792839
    ],
    "val_losses": [
      0.27457629500111197,
      0.15704781279727154
    ],
    "val_metrics": [
      0.916202229299363,
      0.9535230891719745
    ],
    "ind_losses": [
      0.008760249519677799,
      0.0033390918808222257
    ]
  },
  "config": {
    "seed": 42,
    "seeds": [
      42
    ],
    "device": "cuda",
    "output_root": "results",
    "runs_per_experiment": 5,
    "task": "mnist",
    "dataset": "mnist",
    "data_root": "data/mnist",
    "train_size": 50000,
    "val_size": 10000,
    "download": true,
    "depths": [
      4,
      8,
      16,
      32
    ],
    "models": [
      "mlp",
      "ion"
    ],
    "input_size": 784,
    "hidden_dim": 256,
    "output_size": 10,
    "dropout": 0.0,
    "p_dim": 32,
    "lambda_ind": 0.5,
    "batch_size": 64,
    "num_workers": 0,
    "epochs": 2,
    "lr": 0.001,
    "warmup_epochs": 5,
    "max_grad_norm": 1.0,
    "scheduler": "cosine",
    "lambda_ind_deep": 0.15,
    "depth_threshold_for_lambda": 16,
    "output_type": "classification",
    "num_classes": 10,
    "target_accuracy_for_convergence": 0.95,
    "model": "mlp",
    "num_layers": 4
  },
  "test_accuracy": 0.956906847133758,
  "epochs_to_target_accuracy": 2
}